{"cameraMode":{"drawMode":0,"name":"Shaded","section":"Shading Mode"},"sceneLighting":true,"audioPlay":false,"sceneViewState":{"m_AlwaysRefresh":false,"showFog":true,"showSkybox":true,"showFlares":true,"showImageEffects":true,"showParticleSystems":true,"showVisualEffectGraphs":true,"m_FxEnabled":true},"in2DMode":false,"pivot":{"x":-738.8775634765625,"y":-365.0843811035156,"z":53.390380859375},"rotation":{"x":-0.18252259492874146,"y":0.6599394679069519,"z":-0.17036201059818269,"w":-0.7088057994842529},"size":439.27935791015627,"orthographic":false}